eadpy/__init__.py
eadpy/cli.py
eadpy/ead.py
eadpy/py.typed
eadpy-0.1.3.dist-info/METADATA
eadpy-0.1.3.dist-info/WHEEL
eadpy-0.1.3.dist-info/entry_points.txt
eadpy-0.1.3.dist-info/licenses/LICENSE
eadpy-0.1.3.dist-info/RECORD
