Metadata-Version: 2.4
Name: eadpy
Version: 0.1.3
Summary: A Python library for working with Encoded Archival Description (EAD) XML files
Author-email: Brendan Quinn <brendan-quinn@northwestern.edu>
License-File: LICENSE
Requires-Python: >=3.11
Requires-Dist: lxml>=5.3.1
